{
  "1561500025137-4939.xml": {
    "id": "5d12997840afa60004adccb9",
    "estado": "finalizada",
    "sku": "10006",
    "qty": 1,
    "entrega": "2019-06-25T23:30:00.000Z"
  },
  "1561500025130-6920.xml": {
    "id": "5d12997840afa60004adccb8",
    "estado": "finalizada",
    "sku": "10001",
    "qty": 4,
    "entrega": "2019-06-25T23:30:00.000Z"
  },
  "1561500025135-6424.xml": {
    "id": "5d12997840afa60004adccb7",
    "estado": "finalizada",
    "sku": "30005",
    "qty": 2,
    "entrega": "2019-06-25T23:30:00.000Z"
  },
  "1561503733270-8197.xml": {
    "id": "5d12a7f4392b8a00049ce3f3",
    "estado": "finalizada",
    "sku": "30006",
    "qty": 2,
    "entrega": "2019-06-26T00:32:00.000Z"
  },
  "1561507355700-5710.xml": {
    "id": "5d12b61abcef6700049997a2",
    "estado": "finalizada",
    "sku": "10003",
    "qty": 4,
    "entrega": "2019-06-26T01:32:00.000Z"
  },
  "1561507355700-1715.xml": {
    "id": "5d12b61abcef6700049997a1",
    "estado": "finalizada",
    "sku": "30006",
    "qty": 1,
    "entrega": "2019-06-26T01:32:00.000Z"
  },
  "1561510920351-5159.xml": {
    "id": "5d12c40778780a000476b950",
    "estado": "finalizada",
    "sku": "10013",
    "qty": 4,
    "entrega": "2019-06-26T02:31:00.000Z"
  },
  "1561510920351-1553.xml": {
    "id": "5d12c40778780a000476b951",
    "estado": "finalizada",
    "sku": "30007",
    "qty": 1,
    "entrega": "2019-06-26T02:31:00.000Z"
  },
  "1561514469577-7262.xml": {
    "id": "5d12d1e4b6111a0004299dd9",
    "estado": "cocinando",
    "sku": "10025",
    "qty": 4,
    "entrega": "2019-06-26T03:31:00.000Z"
  }
}